face_embeddings_lib/__init__.py
face_embeddings_lib/engine.py
face_embeddings_lib-0.1.0.dist-info/METADATA
face_embeddings_lib-0.1.0.dist-info/WHEEL
face_embeddings_lib-0.1.0.dist-info/licenses/LICENSE
face_embeddings_lib-0.1.0.dist-info/RECORD
