Metadata-Version: 2.4
Name: face-embeddings-lib
Version: 0.1.0
Summary: A minimal library for extracting face embeddings using YOLO for detection and Facenet for embedding.
License: MIT
License-File: LICENSE
Author: Danil Kabanov
Author-email: danil.d.kabanov@gmail.com
Requires-Python: >=3.10
Classifier: License :: OSI Approved :: MIT License
Classifier: Programming Language :: Python :: 3
Classifier: Programming Language :: Python :: 3.10
Classifier: Programming Language :: Python :: 3.11
Classifier: Programming Language :: Python :: 3.12
Classifier: Programming Language :: Python :: 3.13
Classifier: Programming Language :: Python :: 3.14
Requires-Dist: facenet-pytorch
Requires-Dist: numpy
Requires-Dist: opencv-python
Requires-Dist: torch
Requires-Dist: ultralytics
